{
  "_id": "4eeb7efbc226720fd600002d",
  "first": "Corinna",
  "patient_id": "176",
  "last": "Markos",
  "gender": "F",
  "birthdate": -806011200,
  "race": "Other Race",
  "ethnicity": "Hispanic or Latino",
  "addresses": null,
  "measures": {
    "0001": {
      "encounter_office_outpatient_consult_encounter": [
        1289710800,
        1287288000,
        1284868800,
        1275192000
      ]
    },
    "0002": {
      "encounter_ambulatory_including_pediatrics_encounter": [
        1289710800,
        1287288000,
        1284868800,
        1275192000
      ]
    },
    "0004": {
      "encounter_inpt_ed_non_acute_inpatient_bh_outpatient_encounter": [
        1289710800,
        1287288000,
        1284868800,
        1282795200,
        1282449600,
        1280376000,
        1280030400,
        1275192000
      ],
      "encounter_acute_inpt_encounter": [
        1282795200,
        1282449600,
        1280376000,
        1280030400
      ],
      "encounter_outpatient_bh_encounter": [
        1289710800,
        1287288000,
        1284868800,
        1275192000
      ],
      "encounter_outpt_bh_req_pos_encounter": [
        1282795200,
        1282449600,
        1280376000,
        1280030400
      ]
    },
    "0013": {
      "hypertension_diagnosis_active": [
        1275192000
      ],
      "diastolic_blood_pressure_physical_exam_finding": [
        1289710800,
        1287288000,
        1284868800,
        1277611200,
        1275192000
      ],
      "encounter_outpatient_encounter": [
        1289710800,
        1287288000,
        1284868800,
        1275192000
      ],
      "systolic_blood_pressure_physical_exam_finding": [
        1289710800,
        1287288000,
        1284868800,
        1277611200,
        1275192000
      ]
    },
    "0012": {
      "delivery_live_births_diagnosis_diagnosis_active": [
        1275192000
      ]
    },
    "0014": {
      "delivery_live_births_diagnosis_diagnosis_active": [
        1275192000
      ]
    },
    "0018": {
      "hypertension_diagnosis_active": [
        1275192000
      ],
      "encounter_outpatient_encounter": [
        1289710800,
        1287288000,
        1284868800,
        1275192000
      ],
      "diastolic_blood_pressure_physical_exam_finding": [
        {
          "date": 1289710800,
          "value": 86.0
        },
        {
          "date": 1287288000,
          "value": 86.0
        },
        {
          "date": 1284868800,
          "value": 90.0
        },
        {
          "date": 1277611200,
          "value": 86.0
        },
        {
          "date": 1275192000,
          "value": 84.0
        }
      ],
      "systolic_blood_pressure_physical_exam_finding": [
        {
          "date": 1289710800,
          "value": 136.0
        },
        {
          "date": 1287288000,
          "value": 136.0
        },
        {
          "date": 1284868800,
          "value": 140.0
        },
        {
          "date": 1277611200,
          "value": 136.0
        },
        {
          "date": 1275192000,
          "value": 136.0
        }
      ]
    },
    "0024": {
      "bmi_percentile_physical_exam_finding": [
        1289710800,
        1287288000,
        1284868800,
        1277611200,
        1275192000
      ],
      "encounter_outpatient_w_pcp_obgyn_encounter": [
        1289710800,
        1287288000,
        1284868800,
        1275192000
      ]
    },
    "0027": {
      "encounter_outpatient_encounter": [
        1289710800,
        1287288000,
        1284868800,
        1275192000
      ]
    },
    "0028": {
      "encounter_office_visit_encounter": [
        1289710800,
        1287288000,
        1284868800,
        1275192000
      ]
    },
    "0031": {
      "encounter_outpatient_encounter": [
        1289710800,
        1287288000,
        1284868800,
        1275192000
      ]
    },
    "0032": {
      "encounter_outpatient_encounter": [
        1289710800,
        1287288000,
        1284868800,
        1275192000
      ]
    },
    "0033": {
      "encounter_outpatient_encounter": [
        1289710800,
        1287288000,
        1284868800,
        1275192000
      ]
    },
    "0043": {
      "encounter_outpatient_encounter": [
        1289710800,
        1287288000,
        1284868800,
        1275192000
      ]
    },
    "0086": {
      "primary_open_angle_glaucoma_poag_diagnosis_active": [
        1280030400
      ],
      "encounter_office_outpatient_consult_encounter": [
        1289710800,
        1287288000,
        1284868800,
        1275192000
      ],
      "encounter_ophthalmological_services_encounter": [
        1288411200,
        1277611200
      ],
      "optic_nerve_head_evaluation_procedure_performed": [
        1277611200
      ]
    },
    "0034": {
      "encounter_outpatient_encounter": [
        1289710800,
        1287288000,
        1284868800,
        1275192000
      ]
    },
    "0036": {
      "encounter_outpatient_encounter": [
        1287288000,
        1284868800
      ],
      "encounter_acute_inpt_encounter": [
        1282795200,
        1282449600,
        1280376000,
        1280030400
      ]
    },
    "0038": {
      "encounter_outpatient_w_pcp_obgyn_encounter": [
        1289710800,
        1287288000,
        1284868800,
        1275192000
      ],
      "influenza_vaccine_medication_administered": [
        1289710800
      ]
    },
    "0041": {
      "encounter_influenza_encounter": [
        1289710800,
        1287288000,
        1284868800,
        1275192000
      ],
      "encounter_outpatient_encounter": [
        1289710800,
        1287288000,
        1284868800,
        1275192000
      ],
      "influenza_vaccine_medication_administered": [
        1289710800
      ]
    },
    "0047": {
      "encounter_office_outpatient_consult_encounter": [
        1289710800,
        1287288000,
        1284868800,
        1275192000
      ]
    },
    "0052": {
      "encounter_ambulatory_including_orthopedics_and_chiropractics_encounter": [
        1289710800,
        1287288000,
        1284868800,
        1275192000
      ]
    },
    "0055": {
      "encounter_acute_inpatient_or_ed_encounter": [
        1282795200,
        1282449600,
        1280376000,
        1280030400
      ],
      "encounter_non_acute_inpatient_outpatient_or_ophthalmology_encounter": [
        1289710800,
        1288411200,
        1287288000,
        1284868800,
        1277611200,
        1275192000
      ]
    },
    "0056": {
      "encounter_acute_inpatient_or_ed_encounter": [
        1282795200,
        1282449600,
        1280376000,
        1280030400
      ],
      "encounter_non_acute_inpatient_outpatient_or_ophthalmology_encounter": [
        1289710800,
        1288411200,
        1287288000,
        1284868800,
        1277611200,
        1275192000
      ]
    },
    "0059": {
      "encounter_acute_inpatient_or_ed_encounter": [
        1282795200,
        1282449600,
        1280376000,
        1280030400
      ],
      "encounter_non_acute_inpatient_outpatient_or_ophthalmology_encounter": [
        1289710800,
        1288411200,
        1287288000,
        1284868800,
        1277611200,
        1275192000
      ]
    },
    "0061": {
      "encounter_acute_inpatient_or_ed_encounter": [
        1282795200,
        1282449600,
        1280376000,
        1280030400
      ],
      "encounter_non_acute_inpatient_outpatient_or_ophthalmology_encounter": [
        1289710800,
        1288411200,
        1287288000,
        1284868800,
        1277611200,
        1275192000
      ],
      "diastolic_blood_pressure_physical_exam_finding": [
        {
          "date": 1289710800,
          "value": 86.0
        },
        {
          "date": 1287288000,
          "value": 86.0
        },
        {
          "date": 1284868800,
          "value": 90.0
        },
        {
          "date": 1277611200,
          "value": 86.0
        },
        {
          "date": 1275192000,
          "value": 84.0
        }
      ],
      "systolic_blood_pressure_physical_exam_finding": [
        {
          "date": 1289710800,
          "value": 136.0
        },
        {
          "date": 1287288000,
          "value": 136.0
        },
        {
          "date": 1284868800,
          "value": 140.0
        },
        {
          "date": 1277611200,
          "value": 136.0
        },
        {
          "date": 1275192000,
          "value": 136.0
        }
      ]
    },
    "0062": {
      "ace_inhibitors_arbs_medication_order": [
        1275192000
      ],
      "ace_inhibitors_arbs_medication_dispensed": [
        1275192000
      ],
      "encounter_acute_inpatient_or_ed_encounter": [
        1282795200,
        1282449600,
        1280376000,
        1280030400
      ],
      "encounter_non_acute_inpatient_outpatient_or_ophthalmology_encounter": [
        1289710800,
        1288411200,
        1287288000,
        1284868800,
        1277611200,
        1275192000
      ]
    },
    "0064": {
      "encounter_acute_inpatient_or_ed_encounter": [
        1282795200,
        1282449600,
        1280376000,
        1280030400
      ],
      "encounter_non_acute_inpatient_outpatient_or_ophthalmology_encounter": [
        1289710800,
        1288411200,
        1287288000,
        1284868800,
        1277611200,
        1275192000
      ]
    },
    "0067": {
      "encounter_inpatient_discharge_encounter": [
        1282795200,
        1280376000
      ],
      "encounter_outpatient_encounter": [
        1289710800,
        1287288000,
        1284868800,
        1275192000
      ]
    },
    "0068": {
      "encounter_acute_inpt_and_outpt_encounter": [
        1289710800,
        1287288000,
        1284868800,
        1282795200,
        1282449600,
        1280376000,
        1280030400,
        1275192000
      ],
      "encounter_acute_inpt_encounter": [
        1282795200,
        1282449600,
        1280376000,
        1280030400
      ],
      "encounter_outpatient_encounter": [
        1287288000,
        1284868800
      ]
    },
    "0070": {
      "beta_blocker_therapy_medication_order": [
        1275192000
      ],
      "beta_blocker_therapy_medication_active": [
        1275192000
      ],
      "encounter_inpatient_discharge_encounter": [
        1282795200,
        1280376000
      ],
      "encounter_outpatient_encounter": [
        1289710800,
        1287288000,
        1284868800,
        1275192000
      ],
      "heart_rate_physical_exam_finding": [
        {
          "date": 1289710800,
          "value": 90.0
        },
        {
          "date": 1287288000,
          "value": 86.0
        },
        {
          "date": 1284868800,
          "value": 92.0
        },
        {
          "date": 1277611200,
          "value": 86.0
        },
        {
          "date": 1275192000,
          "value": 86.0
        }
      ]
    },
    "0073": {
      "encounter_acute_inpt_and_outpt_encounter": [
        1289710800,
        1287288000,
        1284868800,
        1282795200,
        1282449600,
        1280376000,
        1280030400,
        1275192000
      ],
      "diastolic_blood_pressure_physical_exam_finding": [
        {
          "date": 1289710800,
          "value": 136.0
        },
        {
          "date": 1287288000,
          "value": 136.0
        },
        {
          "date": 1284868800,
          "value": 140.0
        },
        {
          "date": 1277611200,
          "value": 136.0
        },
        {
          "date": 1275192000,
          "value": 136.0
        }
      ],
      "encounter_acute_inpt_encounter": [
        1282795200,
        1282449600,
        1280376000,
        1280030400
      ],
      "encounter_outpatient_encounter": [
        1287288000,
        1284868800
      ],
      "systolic_blood_pressure_physical_exam_finding": [
        {
          "date": 1289710800,
          "value": 136.0
        },
        {
          "date": 1287288000,
          "value": 136.0
        },
        {
          "date": 1284868800,
          "value": 140.0
        },
        {
          "date": 1277611200,
          "value": 136.0
        },
        {
          "date": 1275192000,
          "value": 136.0
        }
      ]
    },
    "0074": {
      "encounter_outpatient_encounter": [
        1289710800,
        1287288000,
        1284868800,
        1275192000
      ]
    },
    "0075": {
      "encounter_acute_inpt_and_outpt_encounter": [
        1289710800,
        1287288000,
        1284868800,
        1282795200,
        1282449600,
        1280376000,
        1280030400,
        1275192000
      ],
      "encounter_acute_inpt_encounter": [
        1282795200,
        1282449600,
        1280376000,
        1280030400
      ],
      "encounter_outpatient_encounter": [
        1287288000,
        1284868800
      ]
    },
    "0081": {
      "heart_failure_diagnosis_active": [
        1275192000
      ],
      "ace_inhibitor_or_arb_medication_active": [
        1275192000
      ],
      "ace_inhibitor_or_arb_medication_order": [
        1275192000
      ],
      "encounter_inpatient_discharge_encounter": [
        1282795200,
        1280376000
      ],
      "encounter_outpatient_encounter": [
        1289710800,
        1287288000,
        1284868800,
        1275192000
      ]
    },
    "0083": {
      "heart_failure_diagnosis_active": [
        1275192000
      ],
      "beta_blocker_therapy_medication_order": [
        1275192000
      ],
      "beta_blocker_therapy_medication_active": [
        1275192000
      ],
      "encounter_outpatient_encounter": [
        1289710800,
        1287288000,
        1284868800,
        1275192000
      ],
      "heart_rate_physical_exam_finding": [
        1289710800,
        1287288000,
        1284868800,
        1277611200,
        1275192000
      ]
    },
    "0084": {
      "heart_failure_diagnosis_active": [
        1275192000
      ],
      "encounter_outpatient_encounter": [
        1289710800,
        1287288000,
        1284868800,
        1275192000
      ]
    },
    "0088": {
      "encounter_office_outpatient_consult_encounter": [
        1289710800,
        1287288000,
        1284868800,
        1275192000
      ],
      "encounter_ophthalmological_services_encounter": [
        1288411200,
        1277611200
      ]
    },
    "0089": {
      "encounter_office_outpatient_consult_encounter": [
        1289710800,
        1287288000,
        1284868800,
        1275192000
      ],
      "encounter_ophthalmological_services_encounter": [
        1288411200,
        1277611200
      ]
    },
    "0105": {
      "patient_encounter_bh_bh_req_pos_encounter_point_non_acute_inpatient_inpatient_encounter": [
        1289710800,
        1287288000,
        1284868800,
        1282795200,
        1282449600,
        1280376000,
        1280030400,
        1275192000
      ]
    },
    "0385": {
      "encounter_office_visit_encounter": [
        1289710800,
        1287288000,
        1284868800,
        1275192000
      ]
    },
    "0387": {
      "encounter_office_visit_encounter": [
        1289710800,
        1287288000,
        1284868800,
        1275192000
      ]
    },
    "0389": {
    },
    "0421": {
      "encounter_outpatient_encounter": [
        1289710800,
        1287288000,
        1284868800,
        1275192000
      ],
      "follow_up_plan_bmi_management_care_plan": [
        1289710800,
        1275192000
      ],
      "bmi_physical_exam_finding": [
        {
          "date": 1289710800,
          "value": 32.945325443786984
        },
        {
          "date": 1287288000,
          "value": 31.94698224852071
        },
        {
          "date": 1284868800,
          "value": 32.27976331360947
        },
        {
          "date": 1277611200,
          "value": 32.612544378698225
        },
        {
          "date": 1275192000,
          "value": 33.27810650887574
        }
      ],
      "dietary_consultation_order_communication_provider_to_provider": [
        1289710800,
        1275192000
      ]
    },
    "0575": {
      "encounter_acute_inpatient_or_ed_encounter": [
        1282795200,
        1282449600,
        1280376000,
        1280030400
      ],
      "encounter_non_acute_inpatient_outpatient_or_ophthalmology_encounter": [
        1289710800,
        1288411200,
        1287288000,
        1284868800,
        1277611200,
        1275192000
      ]
    }
  },
  "allergies": [

  ],
  "medical_equipment": [

  ],
  "encounters": [
    {
      "codes": {
        "CPT": [
          "99212"
        ]
      },
      "time": 1289710800,
      "description": "Encounter Office Visit"
    },
    {
      "codes": {
        "CPT": [
          "92012"
        ]
      },
      "time": 1288411200,
      "description": "Encounter Ophthalmological Services"
    },
    {
      "codes": {
        "CPT": [
          "99213"
        ],
        "ICD-9-CM": [
          "V70.0"
        ]
      },
      "time": 1287288000,
      "description": "Encounter Outpatient"
    },
    {
      "codes": {
        "CPT": [
          "99213"
        ],
        "ICD-9-CM": [
          "V70.0"
        ]
      },
      "time": 1284868800,
      "description": "Encounter Outpatient"
    },
    {
      "codes": {
        "CPT": [
          "99238"
        ]
      },
      "time": 1282795200,
      "description": "Encounter Inpatient Discharge"
    },
    {
      "codes": {
        "CPT": [
          "99251"
        ]
      },
      "time": 1282449600,
      "description": "encounter acute inpt"
    },
    {
      "codes": {
        "CPT": [
          "99238"
        ]
      },
      "time": 1280376000,
      "description": "Encounter Inpatient Discharge"
    },
    {
      "codes": {
        "CPT": [
          "99251"
        ]
      },
      "time": 1280030400,
      "description": "encounter acute inpt"
    },
    {
      "codes": {
        "CPT": [
          "92012"
        ]
      },
      "time": 1277611200,
      "description": "Encounter Ophthalmological Services"
    },
    {
      "codes": {
        "CPT": [
          "99212"
        ]
      },
      "time": 1275192000,
      "description": "Encounter Office Visit"
    }
  ],
  "social_history": [

  ],
  "vital_signs": [
    {
      "codes": {
        "SNOMED-CT": [
          "271649006"
        ],
        "LOINC": [
          "8480-6"
        ]
      },
      "value": {
        "scalar": 136.0,
        "units": "mm[Hg]"
      },
      "time": 1289710800,
      "description": "Systolic Blood Pressure"
    },
    {
      "codes": {
        "SNOMED-CT": [
          "271650006"
        ],
        "LOINC": [
          "8462-4"
        ]
      },
      "value": {
        "scalar": 86.0,
        "units": "mm[Hg]"
      },
      "time": 1289710800,
      "description": "Diastolic Blood Pressure"
    },
    {
      "codes": {
        "SNOMED-CT": [
          "364075005"
        ]
      },
      "value": {
        "scalar": 90.0,
        "units": null
      },
      "time": 1289710800,
      "description": "Heart Rate"
    },
    {
      "codes": {
        "SNOMED-CT": [
          "271649006"
        ],
        "LOINC": [
          "8480-6"
        ]
      },
      "value": {
        "scalar": 136.0,
        "units": "mm[Hg]"
      },
      "time": 1287288000,
      "description": "Systolic Blood Pressure"
    },
    {
      "codes": {
        "SNOMED-CT": [
          "271650006"
        ],
        "LOINC": [
          "8462-4"
        ]
      },
      "value": {
        "scalar": 86.0,
        "units": "mm[Hg]"
      },
      "time": 1287288000,
      "description": "Diastolic Blood Pressure"
    },
    {
      "codes": {
        "SNOMED-CT": [
          "364075005"
        ]
      },
      "value": {
        "scalar": 86.0,
        "units": null
      },
      "time": 1287288000,
      "description": "Heart Rate"
    },
    {
      "codes": {
        "SNOMED-CT": [
          "271649006"
        ],
        "LOINC": [
          "8480-6"
        ]
      },
      "value": {
        "scalar": 140.0,
        "units": "mm[Hg]"
      },
      "time": 1284868800,
      "description": "Systolic Blood Pressure"
    },
    {
      "codes": {
        "SNOMED-CT": [
          "271650006"
        ],
        "LOINC": [
          "8462-4"
        ]
      },
      "value": {
        "scalar": 90.0,
        "units": "mm[Hg]"
      },
      "time": 1284868800,
      "description": "Diastolic Blood Pressure"
    },
    {
      "codes": {
        "SNOMED-CT": [
          "364075005"
        ]
      },
      "value": {
        "scalar": 92.0,
        "units": null
      },
      "time": 1284868800,
      "description": "Heart Rate"
    },
    {
      "codes": {
        "SNOMED-CT": [
          "271649006"
        ],
        "LOINC": [
          "8480-6"
        ]
      },
      "value": {
        "scalar": 136.0,
        "units": "mm[Hg]"
      },
      "time": 1277611200,
      "description": "Systolic Blood Pressure"
    },
    {
      "codes": {
        "SNOMED-CT": [
          "271650006"
        ],
        "LOINC": [
          "8462-4"
        ]
      },
      "value": {
        "scalar": 86.0,
        "units": "mm[Hg]"
      },
      "time": 1277611200,
      "description": "Diastolic Blood Pressure"
    },
    {
      "codes": {
        "SNOMED-CT": [
          "364075005"
        ]
      },
      "value": {
        "scalar": 86.0,
        "units": null
      },
      "time": 1277611200,
      "description": "Heart Rate"
    },
    {
      "codes": {
        "SNOMED-CT": [
          "271649006"
        ],
        "LOINC": [
          "8480-6"
        ]
      },
      "value": {
        "scalar": 136.0,
        "units": "mm[Hg]"
      },
      "time": 1275192000,
      "description": "Systolic Blood Pressure"
    },
    {
      "codes": {
        "SNOMED-CT": [
          "271650006"
        ],
        "LOINC": [
          "8462-4"
        ]
      },
      "value": {
        "scalar": 84.0,
        "units": "mm[Hg]"
      },
      "time": 1275192000,
      "description": "Diastolic Blood Pressure"
    },
    {
      "codes": {
        "SNOMED-CT": [
          "364075005"
        ]
      },
      "value": {
        "scalar": 86.0,
        "units": null
      },
      "time": 1275192000,
      "description": "Heart Rate"
    },
    {
      "codes": {
        "SNOMED-CT": [
          "60621009"
        ],
        "LOINC": [
          "39156-5"
        ]
      },
      "value": {
        "scalar": 32.945325443786984,
        "units": null
      },
      "time": 1289710800,
      "description": "BMI"
    },
    {
      "codes": {
        "SNOMED-CT": [
          "60621009"
        ],
        "LOINC": [
          "39156-5"
        ]
      },
      "value": {
        "scalar": 31.94698224852071,
        "units": null
      },
      "time": 1287288000,
      "description": "BMI"
    },
    {
      "codes": {
        "SNOMED-CT": [
          "60621009"
        ],
        "LOINC": [
          "39156-5"
        ]
      },
      "value": {
        "scalar": 32.27976331360947,
        "units": null
      },
      "time": 1284868800,
      "description": "BMI"
    },
    {
      "codes": {
        "SNOMED-CT": [
          "60621009"
        ],
        "LOINC": [
          "39156-5"
        ]
      },
      "value": {
        "scalar": 32.612544378698225,
        "units": null
      },
      "time": 1277611200,
      "description": "BMI"
    },
    {
      "codes": {
        "SNOMED-CT": [
          "60621009"
        ],
        "LOINC": [
          "39156-5"
        ]
      },
      "value": {
        "scalar": 33.27810650887574,
        "units": null
      },
      "time": 1275192000,
      "description": "BMI"
    }
  ],
  "conditions": [
    {
      "codes": {
        "ICD-9-CM": [
          "428.9"
        ],
        "ICD-10-CM": [
          "I50.9"
        ],
        "SNOMED-CT": [
          "84114007"
        ]
      },
      "time": 1275192000,
      "status": "active",
      "description": "Heart Failure"
    },
    {
      "codes": {
        "ICD-9-CM": [
          "365.10"
        ],
        "ICD-10-CM": [
          "H40.13"
        ],
        "SNOMED-CT": [
          "84494001"
        ]
      },
      "time": 1280030400,
      "status": "active",
      "description": "Primary Open Angle Glaucoma (POAG)"
    },
    {
      "codes": {
        "ICD-9-CM": [
          "401.9"
        ],
        "ICD-10-CM": [
          "I10"
        ],
        "SNOMED-CT": [
          "59621000"
        ]
      },
      "time": 1275192000,
      "status": "active",
      "description": "Hypertension"
    }
  ],
  "results": [

  ],
  "procedures": [
    {
      "codes": {
        "SNOMED-CT": [
          "103699006"
        ]
      },
      "time": 1289710800,
      "description": "dietary consultation order"
    },
    {
      "codes": {
        "SNOMED-CT": [
          "103699006"
        ]
      },
      "time": 1275192000,
      "description": "dietary consultation order"
    },
    {
      "codes": {
        "SNOMED-CT": [
          "36228007"
        ]
      },
      "time": 1277611200,
      "description": "Optic Nerve Head Evaluation"
    },
    {
      "codes": {
        "CPT": [
          "93543"
        ]
      },
      "time": 1282449600,
      "description": "LVF Assessment"
    },
    {
      "codes": {
        "SNOMED-CT": [
          "70822001"
        ]
      },
      "time": 1280030400,
      "description": "Ejection Fraction"
    }
  ],
  "medications": [
    {
      "codes": {
        "RxNorm": [
          "314076"
        ]
      },
      "time": 1275192000,
      "description": "ACE inhibitor or ARB"
    },
    {
      "codes": {
        "RxNorm": [
          "866924"
        ]
      },
      "time": 1275192000,
      "description": "Beta Blocker Therapy"
    }
  ],
  "immunizations": [
    {
      "codes": {
        "RxNorm": [
          "857942"
        ]
      },
      "time": 1289710800,
      "description": "Influenza Vaccine"
    },
    {
      "codes": {
        "CVX": [
          "100"
        ],
        "CPT": [
          "90669"
        ]
      },
      "time": 1289710800,
      "description": "Pneumococcal Vaccine all ages"
    }
  ],
  "care_goals": [
    {
      "codes": {
        "CPT": [
          "97804"
        ],
        "HCPCS": [
          "S9470"
        ],
        "SNOMED-CT": [
          "305849009"
        ],
        "ICD-9-CM": [
          "V65.3"
        ]
      },
      "time": 1289710800,
      "description": "follow-up plan_BMI management"
    },
    {
      "codes": {
        "CPT": [
          "97804"
        ],
        "HCPCS": [
          "S9470"
        ],
        "SNOMED-CT": [
          "305849009"
        ],
        "ICD-9-CM": [
          "V65.3"
        ]
      },
      "time": 1275192000,
      "description": "follow-up plan_BMI management"
    }
  ]
}