{
  "_id": "4fe1ecaca9ffcc03cd0000b6",
  "birthdate": 106977600,
  "conditions": [
    {
      "_id": "4fe1ecaca9ffcc03cd0000c9",
      "causeOfDeath": null,
      "codes": {
        "ICD-9-CM": [
          "365.10"
        ],
        "ICD-10-CM": [
          "H40.13"
        ],
        "SNOMED-CT": [
          "84494001"
        ]
      },
      "description": "Primary Open Angle Glaucoma (POAG)",
      "element_name": null,
      "end_time": null,
      "free_text": null,
      "mood_code": "EVN",
      "name": null,
      "ordinality": "principal",
      "priority": null,
      "specifics": "C0017612:Glaucoma, Open-Angle;",
      "start_time": null,
      "status": "active",
      "time": 1277956800,
      "type": null,
      "value": {
      }
    },
    {
      "_id": "4fe1ecaca9ffcc03cd0000ca",
      "causeOfDeath": null,
      "codes": {
        "ICD-9-CM": [
          "250"
        ],
        "ICD-10-CM": [
          "E11.9"
        ],
        "SNOMED-CT": [
          "73211009"
        ]
      },
      "description": "diabetes",
      "element_name": null,
      "end_time": null,
      "free_text": null,
      "mood_code": "EVN",
      "name": null,
      "ordinality": "principal",
      "priority": null,
      "specifics": "C0011849:Diabetes Mellitus;",
      "start_time": null,
      "status": "active",
      "time": 1270008000,
      "type": null,
      "value": {
      }
    },
    {
      "_id": "4fe1ecaca9ffcc03cd0000cb",
      "causeOfDeath": null,
      "codes": {
        "ICD-9-CM": [
          "401.9"
        ],
        "ICD-10-CM": [
          "I10"
        ],
        "SNOMED-CT": [
          "59621000"
        ]
      },
      "description": "Hypertension",
      "element_name": null,
      "end_time": null,
      "free_text": null,
      "mood_code": "EVN",
      "name": null,
      "ordinality": "principal",
      "priority": null,
      "specifics": "C2882073:hypertension (arterial) (benign) (essential) (malignant) (primary) (systemic); C0020538:Hypertensive disease; C0085580:Essential Hypertension;",
      "start_time": null,
      "status": "active",
      "time": 1270008000,
      "type": null,
      "value": {
      }
    }
  ],
  "deathdate": null,
  "effective_time": null,
  "encounters": [
    {
      "_id": "4fe1ecaca9ffcc03cd0000b7",
      "admitType": null,
      "codes": {
        "CPT": [
          "99241"
        ]
      },
      "description": "Encounter Office & Outpatient Consult",
      "dischargeDisposition": null,
      "element_name": null,
      "end_time": null,
      "free_text": null,
      "mood_code": "EVN",
      "performer_id": null,
      "specifics": "C0199299:Office consultation for a new or established patient, which requires these 3 key components: A problem focused history; A problem focused examination; and Straightforward medical decision making. Counseling and/or coordination of care with other providers or agencies are provided consistent with the nature of the problem(s) and the patient's and/or family's needs. Usually, the presenting problem(s) are self limited or minor. Physicians typically spend 15 minutes face-to-face with the patient and/or family.;",
      "start_time": null,
      "status": null,
      "time": 1289970000,
      "value": {
      }
    },
    {
      "_id": "4fe1ecaca9ffcc03cd0000b8",
      "admitType": null,
      "codes": {
        "CPT": [
          "99213"
        ],
        "ICD-9-CM": [
          "V70.0"
        ]
      },
      "description": "Encounter Outpatient",
      "dischargeDisposition": null,
      "element_name": null,
      "end_time": null,
      "free_text": null,
      "mood_code": "EVN",
      "performer_id": null,
      "specifics": "C0374559:Office or other outpatient visit for the evaluation and management of an established patient, which requires at least 2 of these 3 key components: An expanded problem focused history; An expanded problem focused examination; Medical decision making of low complexity. Counseling and coordination of care with other providers or agencies are provided consistent with the nature of the problem(s) and the patient's and/or family's needs. Usually, the presenting problem(s) are of low to moderate severity. Physicians typically spend 15 minutes face-to-face with the patient and/or family.;",
      "start_time": null,
      "status": null,
      "time": 1282017600,
      "value": {
      }
    },
    {
      "_id": "4fe1ecaca9ffcc03cd0000b9",
      "admitType": null,
      "codes": {
        "CPT": [
          "99241"
        ]
      },
      "description": "Encounter Office & Outpatient Consult",
      "dischargeDisposition": null,
      "element_name": null,
      "end_time": null,
      "free_text": null,
      "mood_code": "EVN",
      "performer_id": null,
      "specifics": "C0199299:Office consultation for a new or established patient, which requires these 3 key components: A problem focused history; A problem focused examination; and Straightforward medical decision making. Counseling and/or coordination of care with other providers or agencies are provided consistent with the nature of the problem(s) and the patient's and/or family's needs. Usually, the presenting problem(s) are self limited or minor. Physicians typically spend 15 minutes face-to-face with the patient and/or family.;",
      "start_time": null,
      "status": null,
      "time": 1277956800,
      "value": {
      }
    },
    {
      "_id": "4fe1ecaca9ffcc03cd0000ba",
      "admitType": null,
      "codes": {
        "CPT": [
          "99213"
        ],
        "ICD-9-CM": [
          "V70.0"
        ]
      },
      "description": "Encounter Outpatient",
      "dischargeDisposition": null,
      "element_name": null,
      "end_time": null,
      "free_text": null,
      "mood_code": "EVN",
      "performer_id": null,
      "specifics": "C0374559:Office or other outpatient visit for the evaluation and management of an established patient, which requires at least 2 of these 3 key components: An expanded problem focused history; An expanded problem focused examination; Medical decision making of low complexity. Counseling and coordination of care with other providers or agencies are provided consistent with the nature of the problem(s) and the patient's and/or family's needs. Usually, the presenting problem(s) are of low to moderate severity. Physicians typically spend 15 minutes face-to-face with the patient and/or family.;",
      "start_time": null,
      "status": null,
      "time": 1270008000,
      "value": {
      }
    }
  ],
  "ethnicity": {
    "name": "Not Hispanic or Latino",
    "code": "2186-5"
  },
  "first": "Cara",
  "gender": "F",
  "immunizations": [
    {
      "_id": "4fe1ecaca9ffcc03cd0000de",
      "codes": {
        "RxNorm": [
          "857942"
        ]
      },
      "description": "Influenza Vaccine",
      "element_name": null,
      "end_time": null,
      "free_text": null,
      "mood_code": "EVN",
      "performer_id": null,
      "refusalInd": null,
      "refusalReason": null,
      "seriesNumber": null,
      "specifics": "C2718407:Influenza Virus Vaccine, Inactivated A-Brisbane-59-2007, IVR-148 (H1N1) strain 0.03 MG/ML / Influenza Virus Vaccine, Inactivated A-Uruguay-716-2007, NYMC X-175C (H3N2) strain 0.03 MG/ML / Influenza Virus Vaccine, Inactivated B-Brisbane-60-2008 strain 0.03 MG/ML Injectable Suspension;",
      "start_time": null,
      "status": null,
      "time": 1289970000,
      "value": {
      }
    },
    {
      "_id": "4fe1ecaca9ffcc03cd0000df",
      "codes": {
        "CVX": [
          "100"
        ],
        "CPT": [
          "90669"
        ]
      },
      "description": "Pneumococcal Vaccine all ages",
      "element_name": null,
      "end_time": null,
      "free_text": null,
      "mood_code": "EVN",
      "performer_id": null,
      "refusalInd": null,
      "refusalReason": null,
      "seriesNumber": null,
      "specifics": "C2724348:Pneumococcal conjugate vaccine, 7 valent, for intramuscular use;",
      "start_time": null,
      "status": null,
      "time": 1289970000,
      "value": {
      }
    }
  ],
  "languages": null,
  "last": "Dolan",
  "measures": {
    "0001": {
      "encounter_office_outpatient_consult_encounter": [
        1289970000,
        1282017600,
        1277956800,
        1270008000
      ]
    },
    "0002": {
      "encounter_ambulatory_including_pediatrics_encounter": [
        1289970000,
        1282017600,
        1277956800,
        1270008000
      ]
    },
    "0004": {
      "encounter_inpt_ed_non_acute_inpatient_bh_outpatient_encounter": [
        1289970000,
        1282017600,
        1277956800,
        1270008000
      ],
      "encounter_outpatient_bh_encounter": [
        1289970000,
        1282017600,
        1277956800,
        1270008000
      ]
    },
    "0013": {
      "hypertension_diagnosis_active": [
        1270008000
      ],
      "diastolic_blood_pressure_physical_exam_finding": [
        1289970000,
        1282017600,
        1277956800,
        1270008000
      ],
      "encounter_outpatient_encounter": [
        1289970000,
        1282017600,
        1277956800,
        1270008000
      ],
      "systolic_blood_pressure_physical_exam_finding": [
        1289970000,
        1282017600,
        1277956800,
        1270008000
      ]
    },
    "0012": {
      "delivery_live_births_diagnosis_diagnosis_active": [
        1270008000
      ]
    },
    "0014": {
      "delivery_live_births_diagnosis_diagnosis_active": [
        1270008000
      ]
    },
    "0018": {
      "hypertension_diagnosis_active": [
        1270008000
      ],
      "encounter_outpatient_encounter": [
        1289970000,
        1282017600,
        1277956800,
        1270008000
      ],
      "diastolic_blood_pressure_physical_exam_finding": [
        {
          "date": 1289970000,
          "value": 78.0
        },
        {
          "date": 1282017600,
          "value": 76.0
        },
        {
          "date": 1277956800,
          "value": 76.0
        },
        {
          "date": 1270008000,
          "value": 78.0
        }
      ],
      "systolic_blood_pressure_physical_exam_finding": [
        {
          "date": 1289970000,
          "value": 130.0
        },
        {
          "date": 1282017600,
          "value": 128.0
        },
        {
          "date": 1277956800,
          "value": 130.0
        },
        {
          "date": 1270008000,
          "value": 132.0
        }
      ]
    },
    "0024": {
      "bmi_percentile_physical_exam_finding": [
        1289970000,
        1282881600,
        1282017600,
        1277956800,
        1270008000
      ],
      "encounter_outpatient_w_pcp_obgyn_encounter": [
        1289970000,
        1282017600,
        1277956800,
        1270008000
      ]
    },
    "0027": {
      "encounter_outpatient_encounter": [
        1289970000,
        1282017600,
        1277956800,
        1270008000
      ]
    },
    "0028": {
      "encounter_office_visit_encounter": [
        1282017600,
        1270008000
      ],
      "tobacco_non_user_patient_characteristic": [
        1270008000
      ]
    },
    "0031": {
      "encounter_outpatient_encounter": [
        1289970000,
        1282017600,
        1277956800,
        1270008000
      ]
    },
    "0032": {
      "encounter_outpatient_encounter": [
        1289970000,
        1282017600,
        1277956800,
        1270008000
      ],
      "pap_test_laboratory_test_result": [
        1282017600
      ]
    },
    "0033": {
      "encounter_outpatient_encounter": [
        1289970000,
        1282017600,
        1277956800,
        1270008000
      ]
    },
    "0034": {
      "encounter_outpatient_encounter": [
        1289970000,
        1282017600,
        1277956800,
        1270008000
      ]
    },
    "0036": {
      "encounter_outpatient_encounter": [
        1289970000,
        1282017600,
        1277956800,
        1270008000
      ],
      "long_acting_inhaled_beta_2_agonist_medication_active": [
        1277956800
      ],
      "long_acting_inhaled_beta_2_agonist_medication_order": [
        1277956800
      ],
      "long_acting_inhaled_beta_2_agonist_medication_dispensed": [
        1277956800
      ],
      "short_acting_beta_2_agonist_medication_active": [
        1277956800
      ],
      "short_acting_beta_2_agonist_medication_order": [
        1277956800
      ],
      "short_acting_beta_2_agonist_medication_dispensed": [
        1277956800
      ]
    },
    "0038": {
      "encounter_outpatient_w_pcp_obgyn_encounter": [
        1289970000,
        1282017600,
        1277956800,
        1270008000
      ],
      "pneumococcal_vaccination_procedure_performed": [
        1289970000
      ],
      "influenza_vaccine_medication_administered": [
        1289970000
      ]
    },
    "0041": {
      "encounter_influenza_encounter": [
        1289970000,
        1282017600,
        1277956800,
        1270008000
      ],
      "encounter_outpatient_encounter": [
        1289970000,
        1282017600,
        1277956800,
        1270008000
      ],
      "influenza_vaccine_medication_administered": [
        1289970000
      ]
    },
    "0043": {
      "encounter_outpatient_encounter": [
        1289970000,
        1282017600,
        1277956800,
        1270008000
      ],
      "pneumococcal_vaccination_all_ages_procedure_performed": [
        1289970000
      ],
      "pneumococcal_vaccine_all_ages_medication_administered": [
        1289970000
      ]
    },
    "0047": {
      "corticosteroid_inhaled_or_alternative_asthma_medication_medication_active": [
        1277956800
      ],
      "corticosteroid_inhaled_or_alternative_asthma_medication_medication_order": [
        1277956800
      ],
      "encounter_office_outpatient_consult_encounter": [
        1289970000,
        1282017600,
        1277956800,
        1270008000
      ]
    },
    "0052": {
      "encounter_ambulatory_including_orthopedics_and_chiropractics_encounter": [
        1289970000,
        1282017600,
        1277956800,
        1270008000
      ]
    },
    "0055": {
      "diabetes_diagnosis_active": [
        1270008000
      ],
      "encounter_non_acute_inpatient_outpatient_or_ophthalmology_encounter": [
        1289970000,
        1282017600,
        1277956800,
        1270008000
      ],
      "eye_exam_procedure_performed": [
        1282017600
      ],
      "medications_indicative_of_diabetes_medication_dispensed": [
        1270008000
      ],
      "medications_indicative_of_diabetes_medication_order": [
        1270008000
      ],
      "medications_indicative_of_diabetes_medication_active": [
        1270008000
      ]
    },
    "0056": {
      "diabetes_diagnosis_active": [
        1270008000
      ],
      "encounter_non_acute_inpatient_outpatient_or_ophthalmology_encounter": [
        1289970000,
        1282017600,
        1277956800,
        1270008000
      ],
      "medications_indicative_of_diabetes_medication_dispensed": [
        1270008000
      ],
      "medications_indicative_of_diabetes_medication_order": [
        1270008000
      ],
      "medications_indicative_of_diabetes_medication_active": [
        1270008000
      ],
      "foot_exam_physical_exam_performed": [
        1289970000,
        1282017600,
        1277956800,
        1270008000
      ]
    },
    "0059": {
      "diabetes_diagnosis_active": [
        1270008000
      ],
      "encounter_non_acute_inpatient_outpatient_or_ophthalmology_encounter": [
        1289970000,
        1282017600,
        1277956800,
        1270008000
      ],
      "hba1c_test_laboratory_test_result": [
        {
          "date": 1282017600,
          "value": 7.3
        },
        {
          "date": 1270008000,
          "value": 7.1
        }
      ],
      "medications_indicative_of_diabetes_medication_dispensed": [
        1270008000
      ],
      "medications_indicative_of_diabetes_medication_order": [
        1270008000
      ],
      "medications_indicative_of_diabetes_medication_active": [
        1270008000
      ]
    },
    "0061": {
      "diabetes_diagnosis_active": [
        1270008000
      ],
      "encounter_non_acute_inpatient_outpatient_or_ophthalmology_encounter": [
        1289970000,
        1282017600,
        1277956800,
        1270008000
      ],
      "medications_indicative_of_diabetes_medication_dispensed": [
        1270008000
      ],
      "medications_indicative_of_diabetes_medication_order": [
        1270008000
      ],
      "medications_indicative_of_diabetes_medication_active": [
        1270008000
      ],
      "diastolic_blood_pressure_physical_exam_finding": [
        {
          "date": 1289970000,
          "value": 78.0
        },
        {
          "date": 1282017600,
          "value": 76.0
        },
        {
          "date": 1277956800,
          "value": 76.0
        },
        {
          "date": 1270008000,
          "value": 78.0
        }
      ],
      "systolic_blood_pressure_physical_exam_finding": [
        {
          "date": 1289970000,
          "value": 130.0
        },
        {
          "date": 1282017600,
          "value": 128.0
        },
        {
          "date": 1277956800,
          "value": 130.0
        },
        {
          "date": 1270008000,
          "value": 132.0
        }
      ]
    },
    "0062": {
      "ace_inhibitors_arbs_medication_order": [
        1270008000
      ],
      "ace_inhibitors_arbs_medication_dispensed": [
        1270008000
      ],
      "ace_inhibitors_arbs_medication_active": [
        1270008000
      ],
      "diabetes_diagnosis_active": [
        1270008000
      ],
      "encounter_non_acute_inpatient_outpatient_or_ophthalmology_encounter": [
        1289970000,
        1282017600,
        1277956800,
        1270008000
      ],
      "medications_indicative_of_diabetes_medication_dispensed": [
        1270008000
      ],
      "medications_indicative_of_diabetes_medication_order": [
        1270008000
      ],
      "medications_indicative_of_diabetes_medication_active": [
        1270008000
      ],
      "nephropathy_screening_laboratory_test_performed": [
        1270008000
      ]
    },
    "0064": {
      "diabetes_diagnosis_active": [
        1270008000
      ],
      "encounter_non_acute_inpatient_outpatient_or_ophthalmology_encounter": [
        1289970000,
        1282017600,
        1277956800,
        1270008000
      ],
      "ldl_test_laboratory_test_result": [
        {
          "date": 1270008000,
          "value": 75.0
        },
        {
          "date": 1270008000,
          "value": 45.0
        }
      ],
      "medications_indicative_of_diabetes_medication_order": [
        1270008000
      ],
      "medications_indicative_of_diabetes_medication_dispensed": [
        1270008000
      ],
      "medications_indicative_of_diabetes_medication_active": [
        1270008000
      ]
    },
    "0067": {
      "encounter_outpatient_encounter": [
        1289970000,
        1282017600,
        1277956800,
        1270008000
      ]
    },
    "0068": {
      "encounter_acute_inpt_and_outpt_encounter": [
        1289970000,
        1282017600,
        1277956800,
        1270008000
      ],
      "encounter_outpatient_encounter": [
        1282017600,
        1270008000
      ]
    },
    "0070": {
      "encounter_outpatient_encounter": [
        1289970000,
        1282017600,
        1277956800,
        1270008000
      ]
    },
    "0073": {
      "encounter_acute_inpt_and_outpt_encounter": [
        1289970000,
        1282017600,
        1277956800,
        1270008000
      ],
      "diastolic_blood_pressure_physical_exam_finding": [
        {
          "date": 1289970000,
          "value": 130.0
        },
        {
          "date": 1282017600,
          "value": 128.0
        },
        {
          "date": 1277956800,
          "value": 130.0
        },
        {
          "date": 1270008000,
          "value": 132.0
        }
      ],
      "encounter_outpatient_encounter": [
        1282017600,
        1270008000
      ],
      "systolic_blood_pressure_physical_exam_finding": [
        {
          "date": 1289970000,
          "value": 130.0
        },
        {
          "date": 1282017600,
          "value": 128.0
        },
        {
          "date": 1277956800,
          "value": 130.0
        },
        {
          "date": 1270008000,
          "value": 132.0
        }
      ]
    },
    "0074": {
      "encounter_outpatient_encounter": [
        1289970000,
        1282017600,
        1277956800,
        1270008000
      ],
      "ldl_laboratory_test_laboratory_test_result": [
        {
          "date": 1270008000,
          "value": 75.0
        }
      ]
    },
    "0075": {
      "encounter_acute_inpt_and_outpt_encounter": [
        1289970000,
        1282017600,
        1277956800,
        1270008000
      ],
      "high_density_lipoprotein_hdl_laboratory_test_performed": [
        {
          "date": 1270008000,
          "value": 150.0
        },
        {
          "date": 1270008000,
          "value": 45.0
        }
      ],
      "ldl_test_laboratory_test_performed": [
        {
          "date": 1270008000,
          "value": 75.0
        },
        {
          "date": 1270008000,
          "value": 45.0
        }
      ],
      "total_cholesterol_laboratory_test_performed": [
        {
          "date": 1270008000,
          "value": 150.0
        }
      ],
      "triglycerides_laboratory_test_performed": [
        {
          "date": 1270008000,
          "value": 140.0
        }
      ],
      "encounter_outpatient_encounter": [
        1282017600,
        1270008000
      ]
    },
    "0081": {
      "ace_inhibitor_or_arb_medication_active": [
        1270008000
      ],
      "ace_inhibitor_or_arb_medication_order": [
        1270008000
      ],
      "encounter_outpatient_encounter": [
        1289970000,
        1282017600,
        1277956800,
        1270008000
      ]
    },
    "0083": {
      "encounter_outpatient_encounter": [
        1289970000,
        1282017600,
        1277956800,
        1270008000
      ]
    },
    "0084": {
      "encounter_outpatient_encounter": [
        1289970000,
        1282017600,
        1277956800,
        1270008000
      ]
    },
    "0086": {
      "primary_open_angle_glaucoma_poag_diagnosis_active": [
        1277956800
      ],
      "encounter_office_outpatient_consult_encounter": [
        1289970000,
        1282017600,
        1277956800,
        1270008000
      ],
      "optic_nerve_head_evaluation_procedure_performed": [
        1277956800
      ]
    },
    "0088": {
      "encounter_office_outpatient_consult_encounter": [
        1289970000,
        1282017600,
        1277956800,
        1270008000
      ]
    },
    "0089": {
      "encounter_office_outpatient_consult_encounter": [
        1289970000,
        1282017600,
        1277956800,
        1270008000
      ]
    },
    "0105": {
      "patient_encounter_bh_bh_req_pos_encounter_point_non_acute_inpatient_inpatient_encounter": [
        1289970000,
        1282017600,
        1277956800,
        1270008000
      ]
    },
    "0385": {
      "encounter_office_visit_encounter": [
        1282017600,
        1270008000
      ]
    },
    "0387": {
      "encounter_office_visit_encounter": [
        1282017600,
        1270008000
      ]
    },
    "0389": {
    },
    "0421": {
      "encounter_outpatient_encounter": [
        1282017600,
        1270008000
      ],
      "bmi_physical_exam_finding": [
        {
          "date": 1289970000,
          "value": 24.430385386500337
        },
        {
          "date": 1282881600,
          "value": 24.430385386500337
        },
        {
          "date": 1282017600,
          "value": 24.430385386500337
        },
        {
          "date": 1277956800,
          "value": 24.430385386500337
        },
        {
          "date": 1270008000,
          "value": 24.430385386500337
        }
      ]
    },
    "0575": {
      "diabetes_diagnosis_active": [
        1270008000
      ],
      "encounter_non_acute_inpatient_outpatient_or_ophthalmology_encounter": [
        1289970000,
        1282017600,
        1277956800,
        1270008000
      ],
      "hba1c_test_laboratory_test_result": [
        {
          "date": 1282017600,
          "value": 7.3
        },
        {
          "date": 1270008000,
          "value": 7.1
        }
      ],
      "medications_indicative_of_diabetes_medication_dispensed": [
        1270008000
      ],
      "medications_indicative_of_diabetes_medication_order": [
        1270008000
      ],
      "medications_indicative_of_diabetes_medication_active": [
        1270008000
      ]
    }
  },
  "medical_record_number": null,
  "medications": [
    {
      "_id": "4fe1ecaca9ffcc03cd0000da",
      "administrationTiming": null,
      "codes": {
        "RxNorm": [
          "847207"
        ]
      },
      "deliveryMethod": null,
      "description": "Insulin",
      "dose": null,
      "doseIndicator": null,
      "doseRestriction": null,
      "element_name": null,
      "end_time": null,
      "freeTextSig": null,
      "free_text": null,
      "fulfillmentInstructions": null,
      "indication": null,
      "mood_code": "EVN",
      "patientInstructions": null,
      "productForm": null,
      "reaction": null,
      "route": null,
      "site": null,
      "specifics": "C2683559:3 ML Insulin Lispro 100 UNT/ML Prefilled Syringe;",
      "start_time": null,
      "status": null,
      "statusOfMedication": null,
      "time": 1270008000,
      "typeOfMedication": null,
      "value": {
      },
      "vehicle": null
    },
    {
      "_id": "4fe1ecaca9ffcc03cd0000db",
      "administrationTiming": null,
      "codes": {
        "RxNorm": [
          "858828"
        ]
      },
      "deliveryMethod": null,
      "description": "Antihypertensive combinations",
      "dose": null,
      "doseIndicator": null,
      "doseRestriction": null,
      "element_name": null,
      "end_time": null,
      "freeTextSig": null,
      "free_text": null,
      "fulfillmentInstructions": null,
      "indication": null,
      "mood_code": "EVN",
      "patientInstructions": null,
      "productForm": null,
      "reaction": null,
      "route": null,
      "site": null,
      "specifics": "C0976596:Enalapril Maleate 10 MG / Hydrochlorothiazide 25 MG Oral Tablet;",
      "start_time": null,
      "status": null,
      "statusOfMedication": null,
      "time": 1270008000,
      "typeOfMedication": null,
      "value": {
      },
      "vehicle": null
    },
    {
      "_id": "4fe1ecaca9ffcc03cd0000dc",
      "administrationTiming": null,
      "codes": {
        "RxNorm": [
          "318142"
        ]
      },
      "deliveryMethod": null,
      "description": "Long acting inhaled beta 2 agonist",
      "dose": null,
      "doseIndicator": null,
      "doseRestriction": null,
      "element_name": null,
      "end_time": null,
      "freeTextSig": null,
      "free_text": null,
      "fulfillmentInstructions": null,
      "indication": null,
      "mood_code": "EVN",
      "patientInstructions": null,
      "productForm": null,
      "reaction": null,
      "route": null,
      "site": null,
      "specifics": "C2731895:60 ACTUAT Fluticasone propionate 0.115 MG/ACTUAT / salmeterol 0.021 MG/ACTUAT Metered Dose Inhaler;",
      "start_time": null,
      "status": null,
      "statusOfMedication": null,
      "time": 1277956800,
      "typeOfMedication": null,
      "value": {
      },
      "vehicle": null
    },
    {
      "_id": "4fe1ecaca9ffcc03cd0000dd",
      "administrationTiming": null,
      "codes": {
        "RxNorm": [
          "630208"
        ]
      },
      "deliveryMethod": null,
      "description": "Short acting beta 2 agonist",
      "dose": null,
      "doseIndicator": null,
      "doseRestriction": null,
      "element_name": null,
      "end_time": null,
      "freeTextSig": null,
      "free_text": null,
      "fulfillmentInstructions": null,
      "indication": null,
      "mood_code": "EVN",
      "patientInstructions": null,
      "productForm": null,
      "reaction": null,
      "route": null,
      "site": null,
      "specifics": "C1696556:Albuterol 0.83 MG/ML Inhalant Solution;",
      "start_time": null,
      "status": null,
      "statusOfMedication": null,
      "time": 1277956800,
      "typeOfMedication": null,
      "value": {
      },
      "vehicle": null
    }
  ],
  "patient_id": "198",
  "procedures": [
    {
      "_id": "4fe1ecaca9ffcc03cd0000d4",
      "codes": {
        "SNOMED-CT": [
          "401191002"
        ]
      },
      "description": "Foot Exam",
      "element_name": null,
      "end_time": null,
      "free_text": null,
      "mood_code": "EVN",
      "performer_id": null,
      "site": null,
      "specifics": "C1303165:Diabetic foot examination;",
      "start_time": null,
      "status": null,
      "time": 1289970000,
      "value": {
        "scalar": "Normal",
        "units": null
      }
    },
    {
      "_id": "4fe1ecaca9ffcc03cd0000d5",
      "codes": {
        "SNOMED-CT": [
          "401191002"
        ]
      },
      "description": "Foot Exam",
      "element_name": null,
      "end_time": null,
      "free_text": null,
      "mood_code": "EVN",
      "performer_id": null,
      "site": null,
      "specifics": "C1303165:Diabetic foot examination;",
      "start_time": null,
      "status": null,
      "time": 1282017600,
      "value": {
        "scalar": "Normal",
        "units": null
      }
    },
    {
      "_id": "4fe1ecaca9ffcc03cd0000d6",
      "codes": {
        "SNOMED-CT": [
          "401191002"
        ]
      },
      "description": "Foot Exam",
      "element_name": null,
      "end_time": null,
      "free_text": null,
      "mood_code": "EVN",
      "performer_id": null,
      "site": null,
      "specifics": "C1303165:Diabetic foot examination;",
      "start_time": null,
      "status": null,
      "time": 1277956800,
      "value": {
        "scalar": "Normal",
        "units": null
      }
    },
    {
      "_id": "4fe1ecaca9ffcc03cd0000d7",
      "codes": {
        "SNOMED-CT": [
          "401191002"
        ]
      },
      "description": "Foot Exam",
      "element_name": null,
      "end_time": null,
      "free_text": null,
      "mood_code": "EVN",
      "performer_id": null,
      "site": null,
      "specifics": "C1303165:Diabetic foot examination;",
      "start_time": null,
      "status": null,
      "time": 1270008000,
      "value": {
        "scalar": "Normal",
        "units": null
      }
    },
    {
      "_id": "4fe1ecaca9ffcc03cd0000d8",
      "codes": {
        "SNOMED-CT": [
          "36228007"
        ]
      },
      "description": "Optic Nerve Head Evaluation",
      "element_name": null,
      "end_time": null,
      "free_text": null,
      "mood_code": "EVN",
      "performer_id": null,
      "site": null,
      "specifics": "C0200149:Ophthalmic examination and evaluation;",
      "start_time": null,
      "status": null,
      "time": 1277956800,
      "value": {
      }
    },
    {
      "_id": "4fe1ecaca9ffcc03cd0000d9",
      "codes": {
        "HCPCS": [
          "S0621"
        ],
        "SNOMED-CT": [
          "390735007"
        ],
        "ICD-9-CM": [
          "95.03"
        ],
        "CPT": [
          "92012"
        ]
      },
      "description": "eye exam",
      "element_name": null,
      "end_time": null,
      "free_text": null,
      "mood_code": "EVN",
      "performer_id": null,
      "site": null,
      "specifics": "C0374194:Ophthalmological services: medical examination and evaluation, with initiation or continuation of diagnostic and treatment program; intermediate, established patient;",
      "start_time": null,
      "status": null,
      "time": 1282017600,
      "value": {
      }
    }
  ],
  "race": {
    "name": "Native Hawaiian or Other Pacific Islander",
    "code": "2076-8"
  },
  "results": [
    {
      "_id": "4fe1ecaca9ffcc03cd0000cc",
      "codes": {
        "ICD-9-CM": [
          "V72.32"
        ],
        "ICD-10-CM": [
          "Z12.4"
        ],
        "CPT": [
          "88174"
        ],
        "HCPCS": [
          "G0147"
        ],
        "LOINC": [
          "10524-7"
        ],
        "SNOMED-CT": [
          "440623000"
        ]
      },
      "description": "Pap Test",
      "element_name": null,
      "end_time": null,
      "free_text": null,
      "interpretation": null,
      "mood_code": "EVN",
      "referenceRange": null,
      "specifics": "C2585782:Microscopic examination of cervical Papanicolaou smear;",
      "start_time": null,
      "status": null,
      "time": 1282017600,
      "value": {
        "scalar": "Negative",
        "units": null
      }
    },
    {
      "_id": "4fe1ecaca9ffcc03cd0000cd",
      "codes": {
        "CPT": [
          "83036"
        ],
        "LOINC": [
          "4548-4"
        ],
        "SNOMED-CT": [
          "43396009"
        ]
      },
      "description": "HbA1c test",
      "element_name": null,
      "end_time": null,
      "free_text": null,
      "interpretation": null,
      "mood_code": "EVN",
      "referenceRange": null,
      "specifics": "C0474680:Hemoglobin A1c measurement;",
      "start_time": null,
      "status": null,
      "time": 1282017600,
      "value": {
        "scalar": 7.3,
        "units": null
      }
    },
    {
      "_id": "4fe1ecaca9ffcc03cd0000ce",
      "codes": {
        "CPT": [
          "83036"
        ],
        "LOINC": [
          "4548-4"
        ],
        "SNOMED-CT": [
          "43396009"
        ]
      },
      "description": "HbA1c test",
      "element_name": null,
      "end_time": null,
      "free_text": null,
      "interpretation": null,
      "mood_code": "EVN",
      "referenceRange": null,
      "specifics": "C0474680:Hemoglobin A1c measurement;",
      "start_time": null,
      "status": null,
      "time": 1270008000,
      "value": {
        "scalar": 7.1,
        "units": null
      }
    },
    {
      "_id": "4fe1ecaca9ffcc03cd0000cf",
      "codes": {
        "CPT": [
          "83721"
        ],
        "LOINC": [
          "2089-1"
        ],
        "SNOMED-CT": [
          "113079009"
        ]
      },
      "description": "LDL",
      "element_name": null,
      "end_time": null,
      "free_text": null,
      "interpretation": null,
      "mood_code": "EVN",
      "referenceRange": null,
      "specifics": "C0202117:Low density lipoprotein cholesterol measurement;",
      "start_time": null,
      "status": null,
      "time": 1270008000,
      "value": {
        "scalar": 75.0,
        "units": null
      }
    },
    {
      "_id": "4fe1ecaca9ffcc03cd0000d0",
      "codes": {
        "CPT": [
          "82465"
        ],
        "LOINC": [
          "2093-3"
        ],
        "SNOMED-CT": [
          "121868005"
        ]
      },
      "description": "Total Cholesterol",
      "element_name": null,
      "end_time": null,
      "free_text": null,
      "interpretation": null,
      "mood_code": "EVN",
      "referenceRange": null,
      "specifics": "C0546633:Cholesterol total measurement;",
      "start_time": null,
      "status": null,
      "time": 1270008000,
      "value": {
        "scalar": 150.0,
        "units": null
      }
    },
    {
      "_id": "4fe1ecaca9ffcc03cd0000d1",
      "codes": {
        "CPT": [
          "84478"
        ],
        "LOINC": [
          "12951-0"
        ],
        "SNOMED-CT": [
          "14740000"
        ]
      },
      "description": "Triglycerides",
      "element_name": null,
      "end_time": null,
      "free_text": null,
      "interpretation": null,
      "mood_code": "EVN",
      "referenceRange": null,
      "specifics": "C0202236:Triglycerides measurement;",
      "start_time": null,
      "status": null,
      "time": 1270008000,
      "value": {
        "scalar": 140.0,
        "units": null
      }
    },
    {
      "_id": "4fe1ecaca9ffcc03cd0000d2",
      "codes": {
        "CPT": [
          "83701"
        ],
        "LOINC": [
          "14646-4"
        ],
        "SNOMED-CT": [
          "28036006"
        ]
      },
      "description": "High Density Lipoprotein (HDL)",
      "element_name": null,
      "end_time": null,
      "free_text": null,
      "interpretation": null,
      "mood_code": "EVN",
      "referenceRange": null,
      "specifics": "C0392885:High density lipoprotein measurement;",
      "start_time": null,
      "status": null,
      "time": 1270008000,
      "value": {
        "scalar": 45.0,
        "units": null
      }
    },
    {
      "_id": "4fe1ecaca9ffcc03cd0000d3",
      "codes": {
        "LOINC": [
          "1754-1"
        ],
        "CPT": [
          "90935"
        ],
        "SNOMED-CT": [
          "171234009"
        ]
      },
      "description": "Nephropathy Screening",
      "element_name": null,
      "end_time": null,
      "free_text": null,
      "interpretation": null,
      "mood_code": "EVN",
      "referenceRange": null,
      "specifics": "C0740222:Nephropathy screen;",
      "start_time": null,
      "status": null,
      "time": 1270008000,
      "value": {
        "scalar": "Negative",
        "units": null
      }
    }
  ],
  "social_history": [
    {
      "_id": "4fe1ecaca9ffcc03cd0000bb",
      "codes": {
        "SNOMED-CT": [
          "160618006"
        ]
      },
      "description": "Tobacco Non-User",
      "element_name": null,
      "end_time": null,
      "free_text": null,
      "mood_code": "EVN",
      "specifics": "C0425311:Current non-smoker;",
      "start_time": null,
      "status": null,
      "time": 1270008000,
      "value": {
        "scalar": null,
        "units": null
      }
    }
  ],
  "test_id": null,
  "vital_signs": [
    {
      "_id": "4fe1ecaca9ffcc03cd0000bc",
      "codes": {
        "SNOMED-CT": [
          "271649006"
        ]
      },
      "description": "Systolic Blood Pressure",
      "element_name": null,
      "end_time": null,
      "free_text": null,
      "interpretation": null,
      "mood_code": "EVN",
      "referenceRange": null,
      "specifics": "C0871470:Systolic Pressure;",
      "start_time": null,
      "status": null,
      "time": 1289970000,
      "value": {
        "scalar": 130.0,
        "units": "mm[Hg]"
      }
    },
    {
      "_id": "4fe1ecaca9ffcc03cd0000bd",
      "codes": {
        "SNOMED-CT": [
          "271650006"
        ]
      },
      "description": "Diastolic Blood Pressure",
      "element_name": null,
      "end_time": null,
      "free_text": null,
      "interpretation": null,
      "mood_code": "EVN",
      "referenceRange": null,
      "specifics": "C0428883:Diastolic blood pressure;",
      "start_time": null,
      "status": null,
      "time": 1289970000,
      "value": {
        "scalar": 78.0,
        "units": "mm[Hg]"
      }
    },
    {
      "_id": "4fe1ecaca9ffcc03cd0000be",
      "codes": {
        "SNOMED-CT": [
          "271649006"
        ]
      },
      "description": "Systolic Blood Pressure",
      "element_name": null,
      "end_time": null,
      "free_text": null,
      "interpretation": null,
      "mood_code": "EVN",
      "referenceRange": null,
      "specifics": "C0871470:Systolic Pressure;",
      "start_time": null,
      "status": null,
      "time": 1282017600,
      "value": {
        "scalar": 128.0,
        "units": "mm[Hg]"
      }
    },
    {
      "_id": "4fe1ecaca9ffcc03cd0000bf",
      "codes": {
        "SNOMED-CT": [
          "271650006"
        ]
      },
      "description": "Diastolic Blood Pressure",
      "element_name": null,
      "end_time": null,
      "free_text": null,
      "interpretation": null,
      "mood_code": "EVN",
      "referenceRange": null,
      "specifics": "C0428883:Diastolic blood pressure;",
      "start_time": null,
      "status": null,
      "time": 1282017600,
      "value": {
        "scalar": 76.0,
        "units": "mm[Hg]"
      }
    },
    {
      "_id": "4fe1ecaca9ffcc03cd0000c0",
      "codes": {
        "SNOMED-CT": [
          "271649006"
        ]
      },
      "description": "Systolic Blood Pressure",
      "element_name": null,
      "end_time": null,
      "free_text": null,
      "interpretation": null,
      "mood_code": "EVN",
      "referenceRange": null,
      "specifics": "C0871470:Systolic Pressure;",
      "start_time": null,
      "status": null,
      "time": 1277956800,
      "value": {
        "scalar": 130.0,
        "units": "mm[Hg]"
      }
    },
    {
      "_id": "4fe1ecaca9ffcc03cd0000c1",
      "codes": {
        "SNOMED-CT": [
          "271650006"
        ]
      },
      "description": "Diastolic Blood Pressure",
      "element_name": null,
      "end_time": null,
      "free_text": null,
      "interpretation": null,
      "mood_code": "EVN",
      "referenceRange": null,
      "specifics": "C0428883:Diastolic blood pressure;",
      "start_time": null,
      "status": null,
      "time": 1277956800,
      "value": {
        "scalar": 76.0,
        "units": "mm[Hg]"
      }
    },
    {
      "_id": "4fe1ecaca9ffcc03cd0000c2",
      "codes": {
        "SNOMED-CT": [
          "271649006"
        ]
      },
      "description": "Systolic Blood Pressure",
      "element_name": null,
      "end_time": null,
      "free_text": null,
      "interpretation": null,
      "mood_code": "EVN",
      "referenceRange": null,
      "specifics": "C0871470:Systolic Pressure;",
      "start_time": null,
      "status": null,
      "time": 1270008000,
      "value": {
        "scalar": 132.0,
        "units": "mm[Hg]"
      }
    },
    {
      "_id": "4fe1ecaca9ffcc03cd0000c3",
      "codes": {
        "SNOMED-CT": [
          "271650006"
        ]
      },
      "description": "Diastolic Blood Pressure",
      "element_name": null,
      "end_time": null,
      "free_text": null,
      "interpretation": null,
      "mood_code": "EVN",
      "referenceRange": null,
      "specifics": "C0428883:Diastolic blood pressure;",
      "start_time": null,
      "status": null,
      "time": 1270008000,
      "value": {
        "scalar": 78.0,
        "units": "mm[Hg]"
      }
    },
    {
      "_id": "4fe1ecaca9ffcc03cd0000c4",
      "codes": {
        "SNOMED-CT": [
          "60621009"
        ],
        "LOINC": [
          "39156-5"
        ]
      },
      "description": "BMI",
      "element_name": null,
      "end_time": null,
      "free_text": null,
      "interpretation": null,
      "mood_code": "EVN",
      "referenceRange": null,
      "specifics": "C1542867:Body mass index:Relative Density:Point in time:^Patient:Quantitative;",
      "start_time": null,
      "status": null,
      "time": 1289970000,
      "value": {
        "scalar": 24.430385386500337,
        "units": null
      }
    },
    {
      "_id": "4fe1ecaca9ffcc03cd0000c5",
      "codes": {
        "SNOMED-CT": [
          "60621009"
        ],
        "LOINC": [
          "39156-5"
        ]
      },
      "description": "BMI",
      "element_name": null,
      "end_time": null,
      "free_text": null,
      "interpretation": null,
      "mood_code": "EVN",
      "referenceRange": null,
      "specifics": "C1542867:Body mass index:Relative Density:Point in time:^Patient:Quantitative;",
      "start_time": null,
      "status": null,
      "time": 1282881600,
      "value": {
        "scalar": 24.430385386500337,
        "units": null
      }
    },
    {
      "_id": "4fe1ecaca9ffcc03cd0000c6",
      "codes": {
        "SNOMED-CT": [
          "60621009"
        ],
        "LOINC": [
          "39156-5"
        ]
      },
      "description": "BMI",
      "element_name": null,
      "end_time": null,
      "free_text": null,
      "interpretation": null,
      "mood_code": "EVN",
      "referenceRange": null,
      "specifics": "C1542867:Body mass index:Relative Density:Point in time:^Patient:Quantitative;",
      "start_time": null,
      "status": null,
      "time": 1282017600,
      "value": {
        "scalar": 24.430385386500337,
        "units": null
      }
    },
    {
      "_id": "4fe1ecaca9ffcc03cd0000c7",
      "codes": {
        "SNOMED-CT": [
          "60621009"
        ],
        "LOINC": [
          "39156-5"
        ]
      },
      "description": "BMI",
      "element_name": null,
      "end_time": null,
      "free_text": null,
      "interpretation": null,
      "mood_code": "EVN",
      "referenceRange": null,
      "specifics": "C1542867:Body mass index:Relative Density:Point in time:^Patient:Quantitative;",
      "start_time": null,
      "status": null,
      "time": 1277956800,
      "value": {
        "scalar": 24.430385386500337,
        "units": null
      }
    },
    {
      "_id": "4fe1ecaca9ffcc03cd0000c8",
      "codes": {
        "SNOMED-CT": [
          "60621009"
        ],
        "LOINC": [
          "39156-5"
        ]
      },
      "description": "BMI",
      "element_name": null,
      "end_time": null,
      "free_text": null,
      "interpretation": null,
      "mood_code": "EVN",
      "referenceRange": null,
      "specifics": "C1542867:Body mass index:Relative Density:Point in time:^Patient:Quantitative;",
      "start_time": null,
      "status": null,
      "time": 1270008000,
      "value": {
        "scalar": 24.430385386500337,
        "units": null
      }
    }
  ]
}