{
  "_id": "4e6a1fca4f85cf3515000055",
  "first": "Angie",
  "patient_id": "33",
  "last": "Kriman",
  "gender": "F",
  "birthdate": -608932800,
  "addresses": null,
  "measures": {
    "0001": {
      "asthma_diagnosis_active": [
        1270008000,
        1270008000
      ],
      "asthma_daytime_symptoms_quantified_symptom_assessed": [
        1274241600,
        1274241600
      ],
      "asthma_nighttime_symptoms_symptom_active": [
        1274241600,
        1274241600
      ],
      "asthma_symptom_assessment_tool_risk_category_assessment": [
        1242792000
      ],
      "encounter_office_outpatient_consult_encounter": [
        1288152000,
        1275796800,
        1271304000,
        1270008000
      ]
    },
    "0002": {
      "encounter_ambulatory_including_pediatrics_encounter": [
        1288152000,
        1275796800,
        1271304000,
        1270008000
      ]
    },
    "0004": {
      "encounter_inpt_ed_non_acute_inpatient_bh_outpatient_encounter": [
        1288152000,
        1275969600,
        1275796800,
        1274241600,
        1271304000,
        1270008000
      ],
      "encounter_acute_inpt_encounter": [
        1275969600,
        1274241600
      ],
      "encounter_outpatient_bh_encounter": [
        1288152000,
        1275796800,
        1271304000,
        1270008000
      ],
      "encounter_outpt_bh_req_pos_encounter": [
        1275969600,
        1274241600
      ]
    },
    "0012": {
    },
    "0013": {
      "hypertension_diagnosis_active": [
        1270008000,
        1270008000
      ],
      "diastolic_blood_pressure_physical_exam_finding": [
        1275796800
      ],
      "encounter_outpatient_encounter": [
        1288152000,
        1275796800,
        1271304000,
        1270008000
      ],
      "systolic_blood_pressure_physical_exam_finding": [
        1275796800
      ]
    },
    "0014": {
    },
    "0018": {
      "hypertension_diagnosis_active": [
        1270008000,
        1270008000
      ],
      "encounter_outpatient_encounter": [
        1288152000,
        1275796800,
        1271304000,
        1270008000
      ],
      "diastolic_blood_pressure_physical_exam_finding": [
        {
          "date": 1275796800,
          "value": 54.0
        }
      ],
      "systolic_blood_pressure_physical_exam_finding": [
        {
          "date": 1275796800,
          "value": 102.0
        }
      ]
    },
    "0024": {
      "bmi_percentile_physical_exam_finding": [
        1288152000,
        1275796800,
        1271304000,
        1270008000,
        1242792000
      ],
      "counseling_for_nutrition_communication_to_patient": [
        1275796800
      ],
      "counseling_for_physical_activity_communication_to_patient": [
        1275796800
      ],
      "encounter_outpatient_w_pcp_obgyn_encounter": [
        1288152000,
        1275796800,
        1271304000,
        1270008000
      ]
    },
    "0027": {
      "encounter_outpatient_encounter": [
        1288152000,
        1275796800,
        1271304000,
        1270008000
      ]
    },
    "0031": {
      "encounter_outpatient_encounter": [
        1288152000,
        1275796800,
        1271304000,
        1270008000
      ]
    },
    "0028": {
      "encounter_office_visit_encounter": [
        1288152000,
        1275796800,
        1271304000,
        1270008000
      ],
      "tobacco_non_user_patient_characteristic": [
        1275796800
      ]
    },
    "0032": {
      "encounter_outpatient_encounter": [
        1288152000,
        1275796800,
        1271304000,
        1270008000
      ]
    },
    "0033": {
      "encounter_outpatient_encounter": [
        1288152000,
        1275796800,
        1271304000,
        1270008000
      ]
    },
    "0034": {
      "colonoscopy_procedure_performed": [
        1275796800
      ],
      "colorectal_cancer_diagnosis_active": [
        1275969600,
        1275969600
      ],
      "encounter_outpatient_encounter": [
        1288152000,
        1275796800,
        1271304000,
        1270008000
      ]
    },
    "0036": {
      "encounter_acute_inpt_encounter": [
        1275969600,
        1274241600
      ],
      "short_acting_beta_2_agonist_medication_active": [
        1274328000,
        1270008000
      ],
      "short_acting_beta_2_agonist_medication_order": [
        1274328000,
        1270008000
      ],
      "short_acting_beta_2_agonist_medication_dispensed": [
        1274328000,
        1270008000
      ]
    },
    "0038": {
      "encounter_outpatient_w_pcp_obgyn_encounter": [
        1288152000,
        1275796800,
        1271304000,
        1270008000
      ],
      "influenza_vaccine_medication_administered": [
        1288152000
      ]
    },
    "0041": {
      "encounter_influenza_encounter": [
        1288152000,
        1275796800,
        1271304000,
        1270008000
      ],
      "encounter_outpatient_encounter": [
        1288152000,
        1275796800,
        1271304000,
        1270008000
      ],
      "influenza_vaccine_medication_administered": [
        1288152000
      ]
    },
    "0043": {
      "encounter_outpatient_encounter": [
        1288152000,
        1275796800,
        1271304000,
        1270008000
      ]
    },
    "0047": {
      "asthma_diagnosis_active": [
        1270008000,
        1270008000
      ],
      "corticosteroid_inhaled_or_alternative_asthma_medication_medication_active": [
        1274328000,
        1270008000
      ],
      "corticosteroid_inhaled_or_alternative_asthma_medication_medication_order": [
        1274328000,
        1270008000
      ],
      "encounter_office_outpatient_consult_encounter": [
        1288152000,
        1275796800,
        1271304000,
        1270008000
      ]
    },
    "0052": {
      "encounter_ambulatory_including_orthopedics_and_chiropractics_encounter": [
        1288152000,
        1275796800,
        1271304000,
        1270008000
      ],
      "low_back_pain_diagnosis_active": [
        1270008000,
        1270008000
      ]
    },
    "0055": {
      "encounter_acute_inpatient_or_ed_encounter": [
        1275969600,
        1274241600
      ],
      "encounter_non_acute_inpatient_outpatient_or_ophthalmology_encounter": [
        1288152000,
        1275796800,
        1271304000,
        1270008000
      ]
    },
    "0056": {
      "encounter_acute_inpatient_or_ed_encounter": [
        1275969600,
        1274241600
      ],
      "encounter_non_acute_inpatient_outpatient_or_ophthalmology_encounter": [
        1288152000,
        1275796800,
        1271304000,
        1270008000
      ]
    },
    "0059": {
      "encounter_acute_inpatient_or_ed_encounter": [
        1275969600,
        1274241600
      ],
      "encounter_non_acute_inpatient_outpatient_or_ophthalmology_encounter": [
        1288152000,
        1275796800,
        1271304000,
        1270008000
      ]
    },
    "0061": {
      "encounter_acute_inpatient_or_ed_encounter": [
        1275969600,
        1274241600
      ],
      "encounter_non_acute_inpatient_outpatient_or_ophthalmology_encounter": [
        1288152000,
        1275796800,
        1271304000,
        1270008000
      ],
      "diastolic_blood_pressure_physical_exam_finding": [
        {
          "date": 1275796800,
          "value": 54.0
        }
      ],
      "systolic_blood_pressure_physical_exam_finding": [
        {
          "date": 1275796800,
          "value": 102.0
        }
      ]
    },
    "0062": {
      "ace_inhibitors_arbs_medication_order": [
        1270008000,
        1276142400
      ],
      "ace_inhibitors_arbs_medication_dispensed": [
        1270008000,
        1276142400
      ],
      "encounter_acute_inpatient_or_ed_encounter": [
        1275969600,
        1274241600
      ],
      "encounter_non_acute_inpatient_outpatient_or_ophthalmology_encounter": [
        1288152000,
        1275796800,
        1271304000,
        1270008000
      ]
    },
    "0064": {
      "encounter_acute_inpatient_or_ed_encounter": [
        1275969600,
        1274241600
      ],
      "encounter_non_acute_inpatient_outpatient_or_ophthalmology_encounter": [
        1288152000,
        1275796800,
        1271304000,
        1270008000
      ],
      "ldl_test_laboratory_test_result": [
        {
          "date": 1275796800,
          "value": 45.0
        },
        {
          "date": 1275796800,
          "value": 69.0
        },
        {
          "date": 1275796800,
          "value": 45.0
        },
        {
          "date": 1275796800,
          "value": 69.0
        }
      ]
    },
    "0067": {
      "encounter_outpatient_encounter": [
        1288152000,
        1275796800,
        1271304000,
        1270008000
      ]
    },
    "0068": {
      "encounter_acute_inpt_and_outpt_encounter": [
        1288152000,
        1275969600,
        1275796800,
        1274241600,
        1271304000,
        1270008000
      ],
      "encounter_acute_inpt_encounter": [
        1275969600,
        1274241600
      ]
    },
    "0070": {
      "asthma_diagnosis_active": [
        1270008000,
        1270008000
      ],
      "encounter_outpatient_encounter": [
        1288152000,
        1275796800,
        1271304000,
        1270008000
      ],
      "heart_rate_physical_exam_finding": [
        {
          "date": 1275796800,
          "value": 76.0
        }
      ]
    },
    "0073": {
      "encounter_acute_inpt_and_outpt_encounter": [
        1288152000,
        1275969600,
        1275796800,
        1274241600,
        1271304000,
        1270008000
      ],
      "diastolic_blood_pressure_physical_exam_finding": [
        {
          "date": 1275796800,
          "value": 102.0
        }
      ],
      "encounter_acute_inpt_encounter": [
        1275969600,
        1274241600
      ],
      "systolic_blood_pressure_physical_exam_finding": [
        {
          "date": 1275796800,
          "value": 102.0
        }
      ]
    },
    "0074": {
      "encounter_outpatient_encounter": [
        1288152000,
        1275796800,
        1271304000,
        1270008000
      ]
    },
    "0075": {
      "encounter_acute_inpt_and_outpt_encounter": [
        1288152000,
        1275969600,
        1275796800,
        1274241600,
        1271304000,
        1270008000
      ],
      "high_density_lipoprotein_hdl_laboratory_test_performed": [
        {
          "date": 1275796800,
          "value": 45.0
        },
        {
          "date": 1275796800,
          "value": 45.0
        }
      ],
      "ldl_test_laboratory_test_performed": [
        {
          "date": 1275796800,
          "value": 45.0
        },
        {
          "date": 1275796800,
          "value": 69.0
        },
        {
          "date": 1275796800,
          "value": 45.0
        },
        {
          "date": 1275796800,
          "value": 69.0
        }
      ],
      "total_cholesterol_laboratory_test_performed": [
        {
          "date": 1275796800,
          "value": 164.0
        },
        {
          "date": 1275796800,
          "value": 164.0
        }
      ],
      "triglycerides_laboratory_test_performed": [
        {
          "date": 1275796800,
          "value": 150.0
        },
        {
          "date": 1275796800,
          "value": 150.0
        }
      ],
      "encounter_acute_inpt_encounter": [
        1275969600,
        1274241600
      ]
    },
    "0081": {
      "ace_inhibitor_or_arb_medication_active": [
        1270008000,
        1276142400
      ],
      "ace_inhibitor_or_arb_medication_order": [
        1270008000,
        1276142400
      ],
      "encounter_outpatient_encounter": [
        1288152000,
        1275796800,
        1271304000,
        1270008000
      ]
    },
    "0083": {
      "asthma_diagnosis_active": [
        1270008000,
        1270008000
      ],
      "encounter_outpatient_encounter": [
        1288152000,
        1275796800,
        1271304000,
        1270008000
      ],
      "heart_rate_physical_exam_finding": [
        1275796800
      ]
    },
    "0084": {
      "encounter_outpatient_encounter": [
        1288152000,
        1275796800,
        1271304000,
        1270008000
      ]
    },
    "0086": {
      "encounter_office_outpatient_consult_encounter": [
        1288152000,
        1275796800,
        1271304000,
        1270008000
      ]
    },
    "0088": {
      "encounter_office_outpatient_consult_encounter": [
        1288152000,
        1275796800,
        1271304000,
        1270008000
      ]
    },
    "0089": {
      "encounter_office_outpatient_consult_encounter": [
        1288152000,
        1275796800,
        1271304000,
        1270008000
      ]
    },
    "0105": {
      "patient_encounter_bh_bh_req_pos_encounter_point_non_acute_inpatient_inpatient_encounter": [
        1288152000,
        1275969600,
        1275796800,
        1274241600,
        1271304000,
        1270008000
      ]
    },
    "0385": {
      "colon_cancer_diagnosis_active": [
        1275969600,
        1275969600
      ],
      "colon_cancer_stage_iii_procedure_result": [
        1275969600
      ],
      "encounter_office_visit_encounter": [
        1288152000,
        1275796800,
        1271304000,
        1270008000
      ]
    },
    "0387": {
      "encounter_office_visit_encounter": [
        1288152000,
        1275796800,
        1271304000,
        1270008000
      ]
    },
    "0389": {
    },
    "0421": {
      "encounter_outpatient_encounter": [
        1288152000,
        1275796800,
        1271304000,
        1270008000
      ],
      "follow_up_plan_bmi_management_care_plan": [
        1275796800
      ],
      "bmi_physical_exam_finding": [
        {
          "date": 1288152000,
          "value": 20.479785969084425
        },
        {
          "date": 1275796800,
          "value": 20.479785969084425
        },
        {
          "date": 1271304000,
          "value": 20.688763376932222
        },
        {
          "date": 1270008000,
          "value": 20.688763376932222
        },
        {
          "date": 1242792000,
          "value": 20.688763376932222
        }
      ]
    },
    "0575": {
      "encounter_acute_inpatient_or_ed_encounter": [
        1275969600,
        1274241600
      ],
      "encounter_non_acute_inpatient_outpatient_or_ophthalmology_encounter": [
        1288152000,
        1275796800,
        1271304000,
        1270008000
      ]
    }
  },
  "allergies": [

  ],
  "medical_equipment": [

  ],
  "encounters": [
    {
      "codes": {
        "CPT": [
          "99213"
        ]
      },
      "time": 1288152000,
      "description": "Encounter Outpatient"
    },
    {
      "codes": {
        "CPT": [
          "99251"
        ]
      },
      "time": 1275969600,
      "description": "encounter acute inpt"
    },
    {
      "codes": {
        "CPT": [
          "99213"
        ]
      },
      "time": 1275796800,
      "description": "Encounter Outpatient"
    },
    {
      "codes": {
        "CPT": [
          "99251"
        ]
      },
      "time": 1274241600,
      "description": "encounter acute inpt"
    },
    {
      "codes": {
        "CPT": [
          "99212"
        ]
      },
      "time": 1271304000,
      "description": "encounter office visit"
    },
    {
      "codes": {
        "CPT": [
          "99212"
        ]
      },
      "time": 1270008000,
      "description": "encounter office visit"
    }
  ],
  "social_history": [
    {
      "codes": {
        "SNOMED-CT": [
          "126838000"
        ]
      },
      "time": 1275969600,
      "status": "active",
      "description": "Colon Cancer"
    },
    {
      "codes": {
        "ICD-9-CM": [
          "493.92"
        ]
      },
      "time": 1270008000,
      "status": "active",
      "description": "Asthma"
    },
    {
      "codes": {
        "ICD-9-CM": [
          "401.9"
        ]
      },
      "time": 1270008000,
      "status": "active",
      "description": "Hypertension"
    },
    {
      "codes": {
        "ICD-9-CM": [
          "724.2"
        ]
      },
      "time": 1270008000,
      "status": "active",
      "description": "low back pain"
    },
    {
      "codes": {
        "SNOMED-CT": [
          "160618006"
        ]
      },
      "time": 1275796800,
      "description": "Tobacco Non-User"
    },
    {
      "codes": {
        "SNOMED-CT": [
          "395022009"
        ]
      },
      "time": 1274241600,
      "description": "Asthma Nighttime Symptoms"
    },
    {
      "codes": {
        "SNOMED-CT": [
          "370202007"
        ]
      },
      "time": 1274241600,
      "description": "Asthma Daytime Symptoms Quantified"
    }
  ],
  "vital_signs": [
    {
      "codes": {
        "SNOMED-CT": [
          "271649006"
        ]
      },
      "value": {
        "scalar": 102.0,
        "units": null
      },
      "time": 1275796800,
      "description": "Systolic Blood Pressure"
    },
    {
      "codes": {
        "SNOMED-CT": [
          "271650006"
        ]
      },
      "value": {
        "scalar": 54.0,
        "units": null
      },
      "time": 1275796800,
      "description": "Diastolic Blood Pressure"
    },
    {
      "codes": {
        "SNOMED-CT": [
          "364075005"
        ]
      },
      "value": {
        "scalar": 76.0,
        "units": null
      },
      "time": 1275796800,
      "description": "Heart Rate"
    },
    {
      "codes": {
        "SNOMED-CT": [
          "60621009"
        ]
      },
      "value": {
        "scalar": 20.479785969084425,
        "units": null
      },
      "time": 1288152000,
      "description": "BMI"
    },
    {
      "codes": {
        "SNOMED-CT": [
          "60621009"
        ]
      },
      "value": {
        "scalar": 20.479785969084425,
        "units": null
      },
      "time": 1275796800,
      "description": "BMI"
    },
    {
      "codes": {
        "SNOMED-CT": [
          "60621009"
        ]
      },
      "value": {
        "scalar": 20.688763376932222,
        "units": null
      },
      "time": 1271304000,
      "description": "BMI"
    },
    {
      "codes": {
        "SNOMED-CT": [
          "60621009"
        ]
      },
      "value": {
        "scalar": 20.688763376932222,
        "units": null
      },
      "time": 1270008000,
      "description": "BMI"
    },
    {
      "codes": {
        "SNOMED-CT": [
          "60621009"
        ]
      },
      "value": {
        "scalar": 20.688763376932222,
        "units": null
      },
      "time": 1242792000,
      "description": "BMI"
    },
    {
      "codes": {
        "CPT": [
          "82465"
        ]
      },
      "value": {
        "scalar": "164mg/dL",
        "units": null
      },
      "time": 1275796800,
      "description": "Total Cholesterol"
    },
    {
      "codes": {
        "CPT": [
          "84478"
        ]
      },
      "value": {
        "scalar": "150mg/dL",
        "units": null
      },
      "time": 1275796800,
      "description": "Triglycerides"
    },
    {
      "codes": {
        "CPT": [
          "83701"
        ]
      },
      "value": {
        "scalar": "45mg/dL",
        "units": null
      },
      "time": 1275796800,
      "description": "High Density Lipoprotein (HDL)"
    },
    {
      "codes": {
        "CPT": [
          "83721"
        ]
      },
      "value": {
        "scalar": "69mg/dL",
        "units": null
      },
      "time": 1275796800,
      "description": "LDL"
    }
  ],
  "conditions": [
    {
      "codes": {
        "SNOMED-CT": [
          "126838000"
        ]
      },
      "time": 1275969600,
      "status": "active",
      "description": "Colon Cancer"
    },
    {
      "codes": {
        "ICD-9-CM": [
          "493.92"
        ]
      },
      "time": 1270008000,
      "status": "active",
      "description": "Asthma"
    },
    {
      "codes": {
        "ICD-9-CM": [
          "401.9"
        ]
      },
      "time": 1270008000,
      "status": "active",
      "description": "Hypertension"
    },
    {
      "codes": {
        "ICD-9-CM": [
          "724.2"
        ]
      },
      "time": 1270008000,
      "status": "active",
      "description": "low back pain"
    },
    {
      "codes": {
        "SNOMED-CT": [
          "395022009"
        ]
      },
      "time": 1274241600,
      "description": "Asthma Nighttime Symptoms"
    },
    {
      "codes": {
        "SNOMED-CT": [
          "370202007"
        ]
      },
      "time": 1274241600,
      "description": "Asthma Daytime Symptoms Quantified"
    }
  ],
  "results": [
    {
      "codes": {
        "CPT": [
          "82465"
        ]
      },
      "value": {
        "scalar": "164mg/dL",
        "units": null
      },
      "time": 1275796800,
      "description": "Total Cholesterol"
    },
    {
      "codes": {
        "CPT": [
          "84478"
        ]
      },
      "value": {
        "scalar": "150mg/dL",
        "units": null
      },
      "time": 1275796800,
      "description": "Triglycerides"
    },
    {
      "codes": {
        "CPT": [
          "83701"
        ]
      },
      "value": {
        "scalar": "45mg/dL",
        "units": null
      },
      "time": 1275796800,
      "description": "High Density Lipoprotein (HDL)"
    },
    {
      "codes": {
        "CPT": [
          "83721"
        ]
      },
      "value": {
        "scalar": "69mg/dL",
        "units": null
      },
      "time": 1275796800,
      "description": "LDL"
    }
  ],
  "procedures": [
    {
      "codes": {
        "CPT": [
          "97802"
        ]
      },
      "time": 1275796800,
      "description": "counseling for nutrition"
    },
    {
      "codes": {
        "ICD-9-CM": [
          "V65.41"
        ]
      },
      "time": 1275796800,
      "description": "counseling for physical activity"
    },
    {
      "codes": {
        "SNOMED-CT": [
          "401011001"
        ]
      },
      "time": 1242792000,
      "description": "Asthma Symptom Assessment Tool"
    },
    {
      "codes": {
        "CPT": [
          "45378"
        ]
      },
      "time": 1275796800,
      "description": "colonoscopy"
    },
    {
      "codes": {
        "SNOMED-CT": [
          "369921003"
        ]
      },
      "time": 1275969600,
      "description": "Colon Cancer Stage III"
    },
    {
      "codes": {
        "SNOMED-CT": [
          "363406005"
        ]
      },
      "time": 1275796800,
      "description": "Colorectal Cancer"
    }
  ],
  "medications": [
    {
      "codes": {
        "RxNorm": [
          "858828"
        ]
      },
      "time": 1270008000,
      "description": "Antihypertensive combinations"
    },
    {
      "codes": {
        "RxNorm": [
          "630208"
        ]
      },
      "time": 1274328000,
      "description": "Short acting beta 2 agonist"
    },
    {
      "codes": {
        "RxNorm": [
          "351136"
        ]
      },
      "time": 1270008000,
      "description": "Corticosteroid, Inhaled or Alternative Asthma Medication"
    },
    {
      "codes": {
        "RxNorm": [
          "314076"
        ]
      },
      "time": 1276142400,
      "description": "ACE inhibitor or ARB"
    }
  ],
  "immunizations": [
    {
      "codes": {
        "RxNorm": [
          "857942"
        ]
      },
      "time": 1288152000,
      "description": "Influenza Vaccine"
    },
    {
      "codes": {
        "CVX": [
          "100"
        ]
      },
      "time": 1288152000,
      "description": "Pneumococcal Vaccine all ages"
    }
  ],
  "care_goals": [
    {
      "codes": {
        "CPT": [
          "97804"
        ]
      },
      "time": 1275796800,
      "description": "follow-up plan_BMI management"
    }
  ],
  "active": [
    {
      "codes": {
        "SNOMED-CT": [
          "126838000"
        ]
      },
      "time": 1275969600,
      "status": "active",
      "description": "Colon Cancer"
    },
    {
      "codes": {
        "ICD-9-CM": [
          "493.92"
        ]
      },
      "time": 1270008000,
      "status": "active",
      "description": "Asthma"
    },
    {
      "codes": {
        "ICD-9-CM": [
          "401.9"
        ]
      },
      "time": 1270008000,
      "status": "active",
      "description": "Hypertension"
    },
    {
      "codes": {
        "ICD-9-CM": [
          "724.2"
        ]
      },
      "time": 1270008000,
      "status": "active",
      "description": "low back pain"
    }
  ],
  "inactive": [

  ],
  "resolved": [

  ]
}